odoo8_addon_account_product_fiscal_classification-8.0.2.1.0.99.dev47-py3.8-nspkg.pth
odoo_addons/account_product_fiscal_classification/README.rst
odoo_addons/account_product_fiscal_classification/__init__.py
odoo_addons/account_product_fiscal_classification/__openerp__.py
odoo_addons/account_product_fiscal_classification/demo/account_product_fiscal_classification.yml
odoo_addons/account_product_fiscal_classification/demo/account_product_fiscal_classification_template.yml
odoo_addons/account_product_fiscal_classification/demo/account_tax.yml
odoo_addons/account_product_fiscal_classification/demo/account_tax_template.yml
odoo_addons/account_product_fiscal_classification/demo/product_template.yml
odoo_addons/account_product_fiscal_classification/demo/res_company.yml
odoo_addons/account_product_fiscal_classification/demo/res_groups.yml
odoo_addons/account_product_fiscal_classification/demo/res_users.yml
odoo_addons/account_product_fiscal_classification/i18n/am.po
odoo_addons/account_product_fiscal_classification/i18n/ar.po
odoo_addons/account_product_fiscal_classification/i18n/bg.po
odoo_addons/account_product_fiscal_classification/i18n/bs.po
odoo_addons/account_product_fiscal_classification/i18n/ca.po
odoo_addons/account_product_fiscal_classification/i18n/ca_ES.po
odoo_addons/account_product_fiscal_classification/i18n/cs.po
odoo_addons/account_product_fiscal_classification/i18n/da.po
odoo_addons/account_product_fiscal_classification/i18n/de.po
odoo_addons/account_product_fiscal_classification/i18n/el_GR.po
odoo_addons/account_product_fiscal_classification/i18n/en_AU.po
odoo_addons/account_product_fiscal_classification/i18n/en_GB.po
odoo_addons/account_product_fiscal_classification/i18n/es.po
odoo_addons/account_product_fiscal_classification/i18n/es_AR.po
odoo_addons/account_product_fiscal_classification/i18n/es_CL.po
odoo_addons/account_product_fiscal_classification/i18n/es_CO.po
odoo_addons/account_product_fiscal_classification/i18n/es_CR.po
odoo8_addon_account_product_fiscal_classification-8.0.2.1.0.99.dev47.dist-info/METADATA
odoo8_addon_account_product_fiscal_classification-8.0.2.1.0.99.dev47.dist-info/WHEEL
odoo8_addon_account_product_fiscal_classification-8.0.2.1.0.99.dev47.dist-info/namespace_packages.txt
odoo8_addon_account_product_fiscal_classification-8.0.2.1.0.99.dev47.dist-info/top_level.txt
odoo8_addon_account_product_fiscal_classification-8.0.2.1.0.99.dev47.dist-info/RECORD
